pyaogmaneo.cpython-312-aarch64-linux-gnu.so
pyaogmaneo.libs/libgomp-d22c30c5.so.1.0.0
pyaogmaneo-2.14.4.dist-info/RECORD
pyaogmaneo-2.14.4.dist-info/WHEEL
pyaogmaneo-2.14.4.dist-info/METADATA
pyaogmaneo-2.14.4.dist-info/top_level.txt
pyaogmaneo-2.14.4.dist-info/licenses/LICENSE.md
